contrxt/__init__.py
contrxt/contrxt.py
contrxt/explain.py
contrxt/trace.py
contrxt/data/__init__.py
contrxt/data/data_manager.py
contrxt/data/tabular_data_manager.py
contrxt/data/text_data_manager.py
contrxt/surrogate/__init__.py
contrxt/surrogate/generic_surrogate.py
contrxt/surrogate/sklearn_surrogate.py
contrxt/util/BDD2Text.py
contrxt/util/__init__.py
contrxt/util/helpers.py
contrxt/util/logger.py
contrxt-0.0.1.dist-info/LICENSE
contrxt-0.0.1.dist-info/METADATA
contrxt-0.0.1.dist-info/WHEEL
contrxt-0.0.1.dist-info/top_level.txt
contrxt-0.0.1.dist-info/RECORD
