Metadata-Version: 2.1
Name: contrxt
Version: 0.0.1
Summary: ContrXT
Home-page: https://github.com/Crisp-Unimib/ContrXT
Author: Andrea Seveso
Author-email: andrea.seveso@unimib.it
License: UNKNOWN
Project-URL: Bug Tracker, https://github.com/Crisp-Unimib/ContrXT/issues
Platform: UNKNOWN
Classifier: Programming Language :: Python :: 3
Classifier: License :: OSI Approved :: MIT License
Classifier: Operating System :: OS Independent
Requires-Python: >=3.6
License-File: LICENSE
Requires-Dist: pandas
Requires-Dist: pydot
Requires-Dist: scikit-learn
Requires-Dist: tqdm
Requires-Dist: stopit
Requires-Dist: graphviz
Requires-Dist: matplotlib
Requires-Dist: apyori
